gotrue/__init__.py
gotrue/_async/__init__.py
gotrue/_async/gotrue_admin_api.py
gotrue/_async/gotrue_admin_mfa_api.py
gotrue/_async/gotrue_base_api.py
gotrue/_async/gotrue_client.py
gotrue/_async/gotrue_mfa_api.py
gotrue/_async/storage.py
gotrue/_sync/__init__.py
gotrue/_sync/api.py
gotrue/_sync/client.py
gotrue/_sync/gotrue_admin_api.py
gotrue/_sync/gotrue_admin_mfa_api.py
gotrue/_sync/gotrue_base_api.py
gotrue/_sync/gotrue_client.py
gotrue/_sync/gotrue_mfa_api.py
gotrue/_sync/storage.py
gotrue/constants.py
gotrue/errors.py
gotrue/helpers.py
gotrue/http_clients.py
gotrue/timer.py
gotrue/types.py
gotrue-2.6.0.dist-info/LICENSE
gotrue-2.6.0.dist-info/METADATA
gotrue-2.6.0.dist-info/WHEEL
gotrue-2.6.0.dist-info/RECORD
