Metadata-Version: 2.1
Name: gotrue
Version: 2.6.0
Summary: Python Client Library for Supabase Auth
Home-page: https://github.com/supabase-community/auth-py
License: MIT
Author: Joel Lee
Author-email: joel@joellee.org
Requires-Python: >=3.8,<4.0
Classifier: License :: OSI Approved :: MIT License
Classifier: Operating System :: OS Independent
Classifier: Programming Language :: Python :: 3
Classifier: Programming Language :: Python :: 3.8
Classifier: Programming Language :: Python :: 3.9
Classifier: Programming Language :: Python :: 3.10
Classifier: Programming Language :: Python :: 3.11
Classifier: Programming Language :: Python :: 3.12
Requires-Dist: httpx[http2] (>=0.24,<0.28)
Requires-Dist: pydantic (>=1.10,<3)
Project-URL: Documentation, https://github.com/supabase-community/auth-py
Project-URL: Repository, https://github.com/supabase-community/auth-py
